sm/__init__.py
sagemaker_local-0.3.0.dist-info/METADATA
sagemaker_local-0.3.0.dist-info/WHEEL
sagemaker_local-0.3.0.dist-info/entry_points.txt
sagemaker_local-0.3.0.dist-info/top_level.txt
sagemaker_local-0.3.0.dist-info/RECORD
